gnani_python_client/__init__.py
gnani_python_client/client.py
gnani_ats_rest_ap-0.0.8.dist-info/METADATA
gnani_ats_rest_ap-0.0.8.dist-info/WHEEL
gnani_ats_rest_ap-0.0.8.dist-info/top_level.txt
gnani_ats_rest_ap-0.0.8.dist-info/RECORD
